jetblack_tomlutils/__init__.py
jetblack_tomlutils/toml_json.py
jetblack_tomlutils-1.0.0.dist-info/entry_points.txt
jetblack_tomlutils-1.0.0.dist-info/WHEEL
jetblack_tomlutils-1.0.0.dist-info/METADATA
jetblack_tomlutils-1.0.0.dist-info/RECORD
