Metadata-Version: 2.1
Name: jetblack-tomlutils
Version: 1.0.0
Summary: Utilities for working with toml files
Home-page: https://github.com/rob-blackbourn/jetblack-tomlutils
License: Apache-2.0
Author: Rob Blackbourn
Author-email: rblackbourn@gmail.com
Requires-Python: >=3.7,<4.0
Classifier: License :: OSI Approved :: Apache Software License
Classifier: Programming Language :: Python :: 3
Classifier: Programming Language :: Python :: 3.7
Requires-Dist: jsonpointer (>=2.0,<3.0)
Requires-Dist: qtoml (>=0.2.4,<0.3.0)
Project-URL: Repository, https://github.com/rob-blackbourn/jetblack-tomlutils
